{
  "id": "uno-ooo-parser",
  "version": "0.1.6",
  "timestamp": "2021-12-26 00:04:59+00:00",
  "name": "XTreeDataModel",
  "type": "interface",
  "namespace": "com.sun.star.awt.tree",
  "parser_args": {
    "sort": true
  },
  "writer_args": {},
  "data": {
    "from_imports": [
      [
        "...lang.x_component",
        "XComponent"
      ]
    ],
    "from_imports_typing": [],
    "quote": [
      "object"
    ],
    "typings": [],
    "name": "XTreeDataModel",
    "imports": [],
    "namespace": "com.sun.star.awt.tree",
    "extends": [
      "com.sun.star.lang.XComponent"
    ],
    "desc": [
      "An instance of this interface is used by the TreeControl to retrieve the hierarchical outline data that is displayed in the actual control.",
      "",
      "If you implement your own XTreeDataModel you need to notify registered XTreeDataModelListener if your model changes after the control is created. If this is not done correctly the TreeControl will not update the data properly.",
      "",
      "If you do not need your own model implementation, you can also use the MutableTreeDataModel."
    ],
    "url": "https://api.libreoffice.org/docs/idl/ref/interfacecom_1_1sun_1_1star_1_1awt_1_1tree_1_1XTreeDataModel.html",
    "items": {
      "methods": [
        {
          "name": "addTreeDataModelListener",
          "returns": "None",
          "desc": [
            "Adds a listener for the TreeDataModelEvent posted after the tree changes."
          ],
          "raises": [],
          "args": [
            [
              "Listener",
              "object",
              "in"
            ]
          ]
        },
        {
          "name": "getRoot",
          "returns": "object",
          "desc": [
            "Returns the root of the tree.",
            "",
            "Returns null only if the tree has no nodes."
          ],
          "raises": [],
          "args": []
        },
        {
          "name": "removeTreeDataModelListener",
          "returns": "None",
          "desc": [
            "Removes a listener previously added with addTreeDataModelListener()."
          ],
          "raises": [],
          "args": [
            [
              "Listener",
              "object",
              "in"
            ]
          ]
        }
      ]
    }
  }
}