{
  "id": "uno-ooo-parser",
  "version": "0.2.9",
  "libre_office_ver": "7.3",
  "name": "UnoControl",
  "type": "service",
  "namespace": "com.sun.star.awt",
  "parser_args": {
    "sort": true,
    "long_names": true,
    "remove_parent_inherited": true
  },
  "writer_args": {
    "include_desc": true
  },
  "data": {
    "allow_db": true,
    "from_imports": [
      [
        "..accessibility.x_accessible",
        "XAccessible",
        "XAccessible_1cbc0eb6"
      ],
      [
        ".x_control",
        "XControl",
        "XControl_7a9c098d"
      ],
      [
        ".x_view",
        "XView",
        "XView_5f670847"
      ],
      [
        ".x_window",
        "XWindow",
        "XWindow_713b0924"
      ]
    ],
    "from_imports_typing": [],
    "extends_map": {
      "com.sun.star.accessibility.XAccessible": "XAccessible_1cbc0eb6",
      "com.sun.star.awt.XControl": "XControl_7a9c098d",
      "com.sun.star.awt.XView": "XView_5f670847",
      "com.sun.star.awt.XWindow": "XWindow_713b0924"
    },
    "quote": [],
    "typings": [],
    "requires_typing": false,
    "full_imports": {
      "general": [
        "com.sun.star.accessibility.XAccessible",
        "com.sun.star.awt.XControl",
        "com.sun.star.awt.XView",
        "com.sun.star.awt.XWindow"
      ],
      "typing": []
    },
    "imports": [],
    "name": "UnoControl",
    "namespace": "com.sun.star.awt",
    "extends": [
      "com.sun.star.awt.XControl",
      "com.sun.star.awt.XWindow",
      "com.sun.star.awt.XView",
      "com.sun.star.accessibility.XAccessible"
    ],
    "desc": [
      "specifies an abstract control.",
      "",
      "All components which implement this service can be integrated in a windowing environment. This service describes the controller of the Smalltalk model view controller design.",
      "",
      "You must set a model and a stub to the UnoControl before using other methods. The implementation only allows the change of the graphics (XView) if the window is not visible. The change of the graphics in visible state should redirect the output to these graphics, but this behavior is implementation-specific.",
      "",
      "The change of data directly at the control may not affect the model data. To ensure this behavior, modify the data of the model.",
      "",
      "**since**",
      "",
      "    OOo 1.1.2"
    ],
    "url": "https://api.libreoffice.org/docs/idl/ref/servicecom_1_1sun_1_1star_1_1awt_1_1UnoControl.html",
    "items": {}
  }
}