{
  "id": "uno-ooo-parser",
  "version": "0.1.23",
  "libre_office_ver": "7.2",
  "name": "SecurityOperationStatus",
  "type": "enum",
  "namespace": "com.sun.star.xml.crypto",
  "parser_args": {
    "sort": true
  },
  "writer_args": {
    "include_desc": true
  },
  "data": {
    "name": "SecurityOperationStatus",
    "namespace": "com.sun.star.xml.crypto",
    "url": "https://api.libreoffice.org/docs/idl/ref/namespacecom_1_1sun_1_1star_1_1xml_1_1crypto.html#ab5d887eb5da1173b766d96d0d863d1dc",
    "allow_db": true,
    "quote": [],
    "typings": [],
    "desc": "",
    "items": [
      {
        "name": "ASSERTION",
        "value": "ASSERTION",
        "desc": []
      },
      {
        "name": "CERT_HAS_EXPIRED",
        "value": "CERT_HAS_EXPIRED",
        "desc": []
      },
      {
        "name": "CERT_ISSUER_FAILED",
        "value": "CERT_ISSUER_FAILED",
        "desc": []
      },
      {
        "name": "CERT_NOT_FOUND",
        "value": "CERT_NOT_FOUND",
        "desc": []
      },
      {
        "name": "CERT_NOT_YET_VALID",
        "value": "CERT_NOT_YET_VALID",
        "desc": []
      },
      {
        "name": "CERT_REVOKED",
        "value": "CERT_REVOKED",
        "desc": []
      },
      {
        "name": "CERT_VERIFY_FAILED",
        "value": "CERT_VERIFY_FAILED",
        "desc": []
      },
      {
        "name": "CRYPTO_FAILED",
        "value": "CRYPTO_FAILED",
        "desc": []
      },
      {
        "name": "DATA_NOT_MATCH",
        "value": "DATA_NOT_MATCH",
        "desc": []
      },
      {
        "name": "DISABLED",
        "value": "DISABLED",
        "desc": []
      },
      {
        "name": "DSIG_INVALID_REFERENCE",
        "value": "DSIG_INVALID_REFERENCE",
        "desc": []
      },
      {
        "name": "DSIG_NO_REFERENCES",
        "value": "DSIG_NO_REFERENCES",
        "desc": []
      },
      {
        "name": "ENGINE_FAILED",
        "value": "ENGINE_FAILED",
        "desc": [
          "The following constants are derived from XMLSec error definitions, as following:",
          "",
          "XMLSEC_ERRORS_R_XMLSEC_FAILED XMLSEC_ERRORS_R_MALLOC_FAILED XMLSEC_ERRORS_R_STRDUP_FAILED XMLSEC_ERRORS_R_CRYPTO_FAILED XMLSEC_ERRORS_R_XML_FAILED XMLSEC_ERRORS_R_XSLT_FAILED XMLSEC_ERRORS_R_IO_FAILED XMLSEC_ERRORS_R_DISABLED XMLSEC_ERRORS_R_NOT_IMPLEMENTED XMLSEC_ERRORS_R_INVALID_SIZE XMLSEC_ERRORS_R_INVALID_DATA XMLSEC_ERRORS_R_INVALID_RESULT XMLSEC_ERRORS_R_INVALID_TYPE XMLSEC_ERRORS_R_INVALID_OPERATION XMLSEC_ERRORS_R_INVALID_STATUS XMLSEC_ERRORS_R_INVALID_FORMAT XMLSEC_ERRORS_R_DATA_NOT_MATCH XMLSEC_ERRORS_R_INVALID_NODE XMLSEC_ERRORS_R_INVALID_NODE_CONTENT XMLSEC_ERRORS_R_INVALID_NODE_ATTRIBUTE XMLSEC_ERRORS_R_MISSING_NODE_ATTRIBUTE XMLSEC_ERRORS_R_NODE_ALREADY_PRESENT XMLSEC_ERRORS_R_UNEXPECTED_NODE XMLSEC_ERRORS_R_NODE_NOT_FOUND XMLSEC_ERRORS_R_INVALID_TRANSFORM XMLSEC_ERRORS_R_INVALID_TRANSFORM_KEY XMLSEC_ERRORS_R_INVALID_URI_TYPE XMLSEC_ERRORS_R_TRANSFORM_SAME_DOCUMENT_REQUIRED XMLSEC_ERRORS_R_TRANSFORM_DISABLED XMLSEC_ERRORS_R_INVALID_KEY_DATA XMLSEC_ERRORS_R_KEY_DATA_NOT_FOUND XMLSEC_ERRORS_R_KEY_DATA_ALREADY_EXIST XMLSEC_ERRORS_R_INVALID_KEY_DATA_SIZE XMLSEC_ERRORS_R_KEY_NOT_FOUND XMLSEC_ERRORS_R_KEYDATA_DISABLED XMLSEC_ERRORS_R_MAX_RETRIEVALS_LEVEL XMLSEC_ERRORS_R_MAX_RETRIEVAL_TYPE_MISMATCH XMLSEC_ERRORS_R_MAX_ENCKEY_LEVEL XMLSEC_ERRORS_R_CERT_VERIFY_FAILED XMLSEC_ERRORS_R_CERT_NOT_FOUND XMLSEC_ERRORS_R_CERT_REVOKED XMLSEC_ERRORS_R_CERT_ISSUER_FAILED XMLSEC_ERRORS_R_CERT_NOT_YET_VALID XMLSEC_ERRORS_R_CERT_HAS_EXPIRED XMLSEC_ERRORS_R_DSIG_NO_REFERENCES XMLSEC_ERRORS_R_DSIG_INVALID_REFERENCE XMLSEC_ERRORS_R_ASSERTION XMLSEC_ERRORS_MAX_NUMBER"
        ]
      },
      {
        "name": "INVALID_DATA",
        "value": "INVALID_DATA",
        "desc": []
      },
      {
        "name": "INVALID_FORMAT",
        "value": "INVALID_FORMAT",
        "desc": []
      },
      {
        "name": "INVALID_KEY_DATA",
        "value": "INVALID_KEY_DATA",
        "desc": []
      },
      {
        "name": "INVALID_KEY_DATA_SIZE",
        "value": "INVALID_KEY_DATA_SIZE",
        "desc": []
      },
      {
        "name": "INVALID_NODE",
        "value": "INVALID_NODE",
        "desc": []
      },
      {
        "name": "INVALID_NODE_ATTRIBUTE",
        "value": "INVALID_NODE_ATTRIBUTE",
        "desc": []
      },
      {
        "name": "INVALID_NODE_CONTENT",
        "value": "INVALID_NODE_CONTENT",
        "desc": []
      },
      {
        "name": "INVALID_OPERATION",
        "value": "INVALID_OPERATION",
        "desc": []
      },
      {
        "name": "INVALID_RESULT",
        "value": "INVALID_RESULT",
        "desc": []
      },
      {
        "name": "INVALID_SIZE",
        "value": "INVALID_SIZE",
        "desc": []
      },
      {
        "name": "INVALID_STATUS",
        "value": "INVALID_STATUS",
        "desc": []
      },
      {
        "name": "INVALID_TRANSFORM",
        "value": "INVALID_TRANSFORM",
        "desc": []
      },
      {
        "name": "INVALID_TRANSFORM_KEY",
        "value": "INVALID_TRANSFORM_KEY",
        "desc": []
      },
      {
        "name": "INVALID_TYPE",
        "value": "INVALID_TYPE",
        "desc": []
      },
      {
        "name": "INVALID_URI_TYPE",
        "value": "INVALID_URI_TYPE",
        "desc": []
      },
      {
        "name": "IO_FAILED",
        "value": "IO_FAILED",
        "desc": []
      },
      {
        "name": "KEYDATA_DISABLED",
        "value": "KEYDATA_DISABLED",
        "desc": []
      },
      {
        "name": "KEY_DATA_ALREADY_EXIST",
        "value": "KEY_DATA_ALREADY_EXIST",
        "desc": []
      },
      {
        "name": "KEY_DATA_NOT_FOUND",
        "value": "KEY_DATA_NOT_FOUND",
        "desc": []
      },
      {
        "name": "KEY_NOT_FOUND",
        "value": "KEY_NOT_FOUND",
        "desc": []
      },
      {
        "name": "MALLOC_FAILED",
        "value": "MALLOC_FAILED",
        "desc": []
      },
      {
        "name": "MAX_ENCKEY_LEVEL",
        "value": "MAX_ENCKEY_LEVEL",
        "desc": []
      },
      {
        "name": "MAX_RETRIEVALS_LEVEL",
        "value": "MAX_RETRIEVALS_LEVEL",
        "desc": []
      },
      {
        "name": "MAX_RETRIEVAL_TYPE_MISMATCH",
        "value": "MAX_RETRIEVAL_TYPE_MISMATCH",
        "desc": []
      },
      {
        "name": "MISSING_NODE_ATTRIBUTE",
        "value": "MISSING_NODE_ATTRIBUTE",
        "desc": []
      },
      {
        "name": "NODE_ALREADY_PRESENT",
        "value": "NODE_ALREADY_PRESENT",
        "desc": []
      },
      {
        "name": "NODE_NOT_FOUND",
        "value": "NODE_NOT_FOUND",
        "desc": []
      },
      {
        "name": "NOT_IMPLEMENTED",
        "value": "NOT_IMPLEMENTED",
        "desc": []
      },
      {
        "name": "OPERATION_SUCCEEDED",
        "value": "OPERATION_SUCCEEDED",
        "desc": []
      },
      {
        "name": "RUNTIMEERROR_FAILED",
        "value": "RUNTIMEERROR_FAILED",
        "desc": []
      },
      {
        "name": "STRDUP_FAILED",
        "value": "STRDUP_FAILED",
        "desc": []
      },
      {
        "name": "TRANSFORM_DISABLED",
        "value": "TRANSFORM_DISABLED",
        "desc": []
      },
      {
        "name": "TRANSFORM_SAME_DOCUMENT_REQUIRED",
        "value": "TRANSFORM_SAME_DOCUMENT_REQUIRED",
        "desc": []
      },
      {
        "name": "UNEXPECTED_NODE",
        "value": "UNEXPECTED_NODE",
        "desc": []
      },
      {
        "name": "UNKNOWN",
        "value": "UNKNOWN",
        "desc": []
      },
      {
        "name": "XML_FAILED",
        "value": "XML_FAILED",
        "desc": []
      },
      {
        "name": "XSLT_FAILED",
        "value": "XSLT_FAILED",
        "desc": []
      }
    ]
  }
}