{
  "id": "uno-ooo-parser",
  "version": "0.1.27",
  "libre_office_ver": "7.2",
  "name": "ExpandVetoException",
  "type": "exception",
  "namespace": "com.sun.star.awt.tree",
  "parser_args": {
    "sort": false,
    "long_names": true,
    "remove_parent_inherited": true
  },
  "writer_args": {
    "include_desc": true
  },
  "data": {
    "allow_db": true,
    "from_imports": [
      [
        "...util.veto_exception",
        "VetoException",
        "VetoException_bdad0c13"
      ]
    ],
    "from_imports_typing": [
      [
        ".tree_expansion_event",
        "TreeExpansionEvent",
        "TreeExpansionEvent_378b0f79"
      ]
    ],
    "extends_map": {
      "com.sun.star.util.VetoException": "VetoException_bdad0c13"
    },
    "quote": [
      "TreeExpansionEvent_378b0f79"
    ],
    "typings": [],
    "requires_typing": true,
    "full_imports": {
      "general": [
        "com.sun.star.util.VetoException"
      ],
      "typing": [
        "com.sun.star.awt.tree.TreeExpansionEvent"
      ]
    },
    "name": "ExpandVetoException",
    "imports": [],
    "namespace": "com.sun.star.awt.tree",
    "extends": [
      "com.sun.star.util.VetoException"
    ],
    "desc": [
      "Exception used to stop an expand/collapse from happening."
    ],
    "url": "https://api.libreoffice.org/docs/idl/ref/exceptioncom_1_1sun_1_1star_1_1awt_1_1tree_1_1ExpandVetoException.html",
    "items": {
      "properties": [
        {
          "name": "Event",
          "returns": "TreeExpansionEvent_378b0f79",
          "origtype": "com.sun.star.awt.tree.TreeExpansionEvent",
          "origin": "com.sun.star.awt.tree.TreeExpansionEvent",
          "desc": [
            "The event that the exception was created for."
          ],
          "raises_get": "",
          "raises_set": ""
        }
      ]
    }
  }
}