{
  "id": "uno-ooo-parser",
  "version": "0.1.16",
  "libre_office_ver": "7.2",
  "name": "FormComponent",
  "type": "service",
  "namespace": "com.sun.star.form",
  "parser_args": {
    "sort": true,
    "long_names": true,
    "remove_parent_inherited": true
  },
  "writer_args": {
    "include_desc": true
  },
  "data": {
    "from_imports": [
      [
        "..beans.x_property_bag",
        "XPropertyBag",
        "beans_x_property_bag_i"
      ],
      [
        "..container.x_named",
        "XNamed",
        "container_x_named_i"
      ],
      [
        ".x_form_component",
        "XFormComponent",
        "x_form_component_i"
      ],
      [
        "..io.x_persist_object",
        "XPersistObject",
        "io_x_persist_object_i"
      ],
      [
        "..lang.x_component",
        "XComponent",
        "lang_x_component_i"
      ]
    ],
    "from_imports_typing": [],
    "extends_map": {
      "com.sun.star.beans.XPropertyBag": "beans_x_property_bag_i",
      "com.sun.star.container.XNamed": "container_x_named_i",
      "com.sun.star.form.XFormComponent": "x_form_component_i",
      "com.sun.star.io.XPersistObject": "io_x_persist_object_i",
      "com.sun.star.lang.XComponent": "lang_x_component_i"
    },
    "quote": [],
    "typings": [],
    "requires_typing": false,
    "name": "FormComponent",
    "imports": [],
    "namespace": "com.sun.star.form",
    "extends": [
      "com.sun.star.form.XFormComponent",
      "com.sun.star.lang.XComponent",
      "com.sun.star.container.XNamed",
      "com.sun.star.io.XPersistObject",
      "com.sun.star.beans.XPropertyBag"
    ],
    "desc": [
      "specifies a component which can be part of a form.",
      "",
      "**since**",
      "",
      "    OOo 2.3"
    ],
    "url": "https://api.libreoffice.org/docs/idl/ref/servicecom_1_1sun_1_1star_1_1form_1_1FormComponent.html",
    "items": {
      "properties": [
        {
          "name": "Name",
          "returns": "str",
          "desc": [
            "the name of the component.",
            "",
            "Note that the name accessed here is the same as when using the com.sun.star.container.XNamed interface."
          ],
          "raises_get": "",
          "raises_set": ""
        }
      ]
    }
  }
}