{
  "id": "uno-ooo-parser",
  "version": "0.1.12",
  "timestamp": "2022-01-02 22:25:43+00:00",
  "type": "struct",
  "name": "RealRectangle3D",
  "namespace": "com.sun.star.geometry",
  "parser_args": {
    "sort": true
  },
  "writer_args": {
    "sort": true,
    "dynamic_struct": false,
    "include_desc": true
  },
  "data": {
    "name": "RealRectangle3D",
    "namespace": "com.sun.star.geometry",
    "url": "https://api.libreoffice.org/docs/idl/ref/structcom_1_1sun_1_1star_1_1geometry_1_1RealRectangle3D.html",
    "from_imports": [],
    "from_imports_typing": [],
    "quote": [],
    "typings": [],
    "requires_typing": false,
    "fullname": "com.sun.star.geometry.RealRectangle3D",
    "desc": [
      "This structure contains the necessary information for a three-dimensional cube.",
      "",
      "**since**",
      "",
      "    OOo 2.0"
    ],
    "imports": [],
    "extends": [],
    "items": [
      {
        "name": "X1",
        "type": "float",
        "lines": [
          "minimum X coordinate."
        ]
      },
      {
        "name": "X2",
        "type": "float",
        "lines": [
          "maximum X coordinate.",
          "",
          "Must be greater than X1 for non-empty cubes.",
          "",
          "."
        ]
      },
      {
        "name": "Y1",
        "type": "float",
        "lines": [
          "minimum Y coordinate."
        ]
      },
      {
        "name": "Y2",
        "type": "float",
        "lines": [
          "maximum Y coordinate.",
          "",
          "Must be greater than Y1 for non-empty cubes."
        ]
      },
      {
        "name": "Z1",
        "type": "float",
        "lines": [
          "minimum Z coordinate."
        ]
      },
      {
        "name": "Z2",
        "type": "float",
        "lines": [
          "maximum Z coordinate.",
          "",
          "Must be greater than Z1 for non-empty cubes."
        ]
      }
    ]
  }
}