{
  "id": "uno-ooo-parser",
  "version": "0.1.10",
  "timestamp": "2021-12-31 23:42:22+00:00",
  "name": "SheetLink",
  "type": "service",
  "namespace": "com.sun.star.sheet",
  "parser_args": {
    "sort": true
  },
  "writer_args": {
    "include_desc": true
  },
  "data": {
    "from_imports": [
      [
        "..util.x_refreshable",
        "XRefreshable"
      ],
      [
        "..beans.x_property_set",
        "XPropertySet"
      ],
      [
        "..container.x_named",
        "XNamed"
      ]
    ],
    "quote": [],
    "typings": [],
    "requires_typing": false,
    "name": "SheetLink",
    "namespace": "com.sun.star.sheet",
    "extends": [
      "com.sun.star.beans.XPropertySet",
      "com.sun.star.util.XRefreshable",
      "com.sun.star.container.XNamed"
    ],
    "url": "https://api.libreoffice.org/docs/idl/ref/servicecom_1_1sun_1_1star_1_1sheet_1_1SheetLink.html",
    "desc": [
      "represents a sheet link.",
      "",
      "A sheet link contains the source data of linked sheets, i.e. the URL and sheet name of the external document.",
      "",
      "To create a linked sheet, the sheet which will be used as linked sheet has to exist already. The method XSheetLinkable.link() creates a SheetLink object in the document's SheetLinks collection and links the sheet to the specified external sheet."
    ]
  }
}