{
  "id": "uno-ooo-parser",
  "version": "0.1.14",
  "libre_office_ver": "7.2",
  "type": "struct",
  "name": "OpenCLPlatform",
  "namespace": "com.sun.star.sheet.opencl",
  "parser_args": {
    "sort": true
  },
  "writer_args": {
    "sort": true,
    "dynamic_struct": false,
    "include_desc": true
  },
  "data": {
    "name": "OpenCLPlatform",
    "namespace": "com.sun.star.sheet.opencl",
    "url": "https://api.libreoffice.org/docs/idl/ref/structcom_1_1sun_1_1star_1_1sheet_1_1opencl_1_1OpenCLPlatform.html",
    "from_imports": [],
    "from_imports_typing": [
      [
        ".open_cl_device",
        "OpenCLDevice"
      ]
    ],
    "quote": [
      "typing.List[OpenCLDevice]"
    ],
    "typings": [
      "typing.List[OpenCLDevice]"
    ],
    "requires_typing": true,
    "fullname": "com.sun.star.sheet.opencl.OpenCLPlatform",
    "desc": [],
    "imports": [],
    "extends": [],
    "items": [
      {
        "name": "Name",
        "type": "str",
        "lines": [
          "The name of the platform as returned by OpenCL."
        ]
      },
      {
        "name": "Vendor",
        "type": "str",
        "lines": []
      },
      {
        "name": "Devices",
        "type": "typing.List[OpenCLDevice]",
        "lines": []
      }
    ]
  }
}