{
  "id": "uno-ooo-parser",
  "version": "0.1.16",
  "libre_office_ver": "7.2",
  "name": "GroupOn",
  "type": "const",
  "namespace": "com.sun.star.report",
  "parser_args": {
    "sort": false,
    "remove_parent_inherited": true
  },
  "writer_args": {
    "hex": false,
    "flags": null
  },
  "data": {
    "name": "GroupOn",
    "namespace": "com.sun.star.report",
    "url": "https://api.libreoffice.org/docs/idl/ref/namespacecom_1_1sun_1_1star_1_1report_1_1GroupOn.html",
    "flags": false,
    "base_class": "ConstIntBase",
    "quote": [],
    "typings": [],
    "requires_typing": false,
    "from_imports": [
      [
        "ooo_uno.base.const",
        "ConstIntBase"
      ]
    ],
    "from_imports_typing": [],
    "fullname": "com.sun.star.report.GroupOn",
    "desc": [
      "Specifies how to group data."
    ],
    "items": [
      {
        "name": "DEFAULT",
        "type": "int",
        "value_type": "INTEGER",
        "value": 0,
        "lines": [
          "The same value in the column value or expression."
        ]
      },
      {
        "name": "PREFIX_CHARACTERS",
        "type": "int",
        "value_type": "INTEGER",
        "value": 1,
        "lines": [
          "The same first nth of characters in the column value or expression."
        ]
      },
      {
        "name": "YEAR",
        "type": "int",
        "value_type": "INTEGER",
        "value": 2,
        "lines": [
          "Dates in the same calendar year."
        ]
      },
      {
        "name": "QUARTAL",
        "type": "int",
        "value_type": "INTEGER",
        "value": 3,
        "lines": [
          "Dates in the same calendar quarter."
        ]
      },
      {
        "name": "MONTH",
        "type": "int",
        "value_type": "INTEGER",
        "value": 4,
        "lines": [
          "Dates in the same month."
        ]
      },
      {
        "name": "WEEK",
        "type": "int",
        "value_type": "INTEGER",
        "value": 5,
        "lines": [
          "Dates in the same week."
        ]
      },
      {
        "name": "DAY",
        "type": "int",
        "value_type": "INTEGER",
        "value": 6,
        "lines": [
          "Dates on the same date."
        ]
      },
      {
        "name": "HOUR",
        "type": "int",
        "value_type": "INTEGER",
        "value": 7,
        "lines": [
          "Times in the same hour."
        ]
      },
      {
        "name": "MINUTE",
        "type": "int",
        "value_type": "INTEGER",
        "value": 8,
        "lines": [
          "Times in the same minute."
        ]
      },
      {
        "name": "INTERVAL",
        "type": "int",
        "value_type": "INTEGER",
        "value": 9,
        "lines": [
          "Values within an interval you specify."
        ]
      }
    ]
  }
}