{
  "id": "uno-ooo-parser",
  "version": "0.1.21",
  "libre_office_ver": "7.2",
  "type": "struct",
  "name": "SingleProofreadingError",
  "namespace": "com.sun.star.linguistic2",
  "parser_args": {
    "sort": false,
    "long_names": true,
    "remove_parent_inherited": true
  },
  "writer_args": {
    "sort": true,
    "dynamic_struct": true,
    "include_desc": true
  },
  "data": {
    "name": "SingleProofreadingError",
    "namespace": "com.sun.star.linguistic2",
    "url": "https://api.libreoffice.org/docs/idl/ref/structcom_1_1sun_1_1star_1_1linguistic2_1_1SingleProofreadingError.html",
    "from_imports": [
      [
        "..beans.property_value",
        "PropertyValue",
        "PropertyValue_c9610c73"
      ]
    ],
    "from_imports_typing": [],
    "extends_map": {
      "com.sun.star.beans.PropertyValue": "PropertyValue_c9610c73"
    },
    "quote": [],
    "typings": [
      "typing.Tuple[PropertyValue_c9610c73, ...]",
      "typing.Tuple[str, ...]"
    ],
    "requires_typing": true,
    "fullname": "com.sun.star.linguistic2.SingleProofreadingError",
    "desc": [
      "holds a single error found by the proofreader.",
      "",
      "**since**",
      "",
      "    OOo 3.0.1"
    ],
    "imports": [],
    "extends": [],
    "items": {
      "properties": [
        {
          "name": "nErrorStart",
          "returns": "int",
          "desc": []
        },
        {
          "name": "nErrorLength",
          "returns": "int",
          "desc": []
        },
        {
          "name": "nErrorType",
          "returns": "int",
          "desc": []
        },
        {
          "name": "aRuleIdentifier",
          "returns": "str",
          "desc": []
        },
        {
          "name": "aShortComment",
          "returns": "str",
          "desc": []
        },
        {
          "name": "aFullComment",
          "returns": "str",
          "desc": []
        }
      ],
      "types": [
        {
          "name": "aSuggestions",
          "returns": "typing.Tuple[str, ...]",
          "desc": []
        },
        {
          "name": "aProperties",
          "returns": "typing.Tuple[PropertyValue_c9610c73, ...]",
          "desc": []
        }
      ]
    }
  }
}