{
  "id": "uno-ooo-parser",
  "version": "0.1.12",
  "timestamp": "2022-01-04 03:27:15+00:00",
  "name": "ResultSet",
  "type": "service",
  "namespace": "com.sun.star.sdb",
  "parser_args": {
    "sort": true
  },
  "writer_args": {
    "include_desc": true
  },
  "data": {
    "from_imports": [
      [
        "..sdbcx.x_columns_supplier",
        "XColumnsSupplier"
      ],
      [
        "..sdbcx.result_set",
        "ResultSet"
      ]
    ],
    "from_imports_typing": [],
    "quote": [],
    "typings": [],
    "requires_typing": false,
    "name": "ResultSet",
    "imports": [],
    "namespace": "com.sun.star.sdb",
    "extends": [
      "com.sun.star.sdbcx.ResultSet",
      "com.sun.star.sdbcx.XColumnsSupplier"
    ],
    "desc": [
      "extends the com.sun.star.sdbcx.ResultSet by a more sophisticated access to the result sets data."
    ],
    "url": "https://api.libreoffice.org/docs/idl/ref/servicecom_1_1sun_1_1star_1_1sdb_1_1ResultSet.html",
    "items": {}
  }
}