{
  "id": "uno-ooo-parser",
  "version": "0.1.17",
  "libre_office_ver": "7.2",
  "name": "XTextConnectionSettings",
  "type": "interface",
  "namespace": "com.sun.star.sdb",
  "parser_args": {
    "sort": true,
    "long_names": true,
    "remove_parent_inherited": true
  },
  "writer_args": {
    "include_desc": true
  },
  "data": {
    "from_imports": [
      [
        "..beans.x_property_set",
        "XPropertySet",
        "beans_x_property_set_i"
      ],
      [
        "..ui.dialogs.x_executable_dialog",
        "XExecutableDialog",
        "ui_dialogs_x_executable_dialog_i"
      ]
    ],
    "from_imports_typing": [],
    "extends_map": {
      "com.sun.star.beans.XPropertySet": "beans_x_property_set_i",
      "com.sun.star.ui.dialogs.XExecutableDialog": "ui_dialogs_x_executable_dialog_i"
    },
    "quote": [],
    "typings": [],
    "requires_typing": false,
    "name": "XTextConnectionSettings",
    "imports": [],
    "namespace": "com.sun.star.sdb",
    "extends": [
      "com.sun.star.ui.dialogs.XExecutableDialog",
      "com.sun.star.beans.XPropertySet"
    ],
    "desc": [
      "",
      "**since**",
      "",
      "    LibreOffice 4.1"
    ],
    "url": "https://api.libreoffice.org/docs/idl/ref/interfacecom_1_1sun_1_1star_1_1sdb_1_1XTextConnectionSettings.html",
    "items": {}
  }
}