{
  "id": "uno-ooo-parser",
  "version": "0.1.15",
  "libre_office_ver": "7.2",
  "name": "Text",
  "type": "service",
  "namespace": "com.sun.star.drawing",
  "parser_args": {
    "sort": true,
    "long_names": true
  },
  "writer_args": {
    "include_desc": true
  },
  "data": {
    "from_imports": [
      [
        ".text_properties",
        "TextProperties",
        "text_properties_i"
      ],
      [
        "..text.x_text",
        "XText",
        "text_x_text_i"
      ]
    ],
    "from_imports_typing": [],
    "extends_map": {
      "com.sun.star.drawing.TextProperties": "text_properties_i",
      "com.sun.star.text.XText": "text_x_text_i"
    },
    "quote": [],
    "typings": [],
    "requires_typing": false,
    "name": "Text",
    "imports": [],
    "namespace": "com.sun.star.drawing",
    "extends": [
      "com.sun.star.text.XText",
      "com.sun.star.drawing.TextProperties"
    ],
    "desc": [
      "This abstract service specifies the general characteristics of an optional text inside a Shape."
    ],
    "url": "https://api.libreoffice.org/docs/idl/ref/servicecom_1_1sun_1_1star_1_1drawing_1_1Text.html",
    "items": {}
  }
}