{
  "id": "uno-ooo-parser",
  "version": "0.4.0",
  "libre_office_ver": "2024.2",
  "name": "InsufficientAccessRightsException",
  "type": "exception",
  "namespace": "com.sun.star.configuration.backend",
  "parser_args": {
    "sort": false,
    "long_names": true,
    "remove_parent_inherited": true
  },
  "writer_args": {
    "include_desc": true
  },
  "data": {
    "allow_db": true,
    "from_imports": [
      [
        ".backend_access_exception",
        "BackendAccessException",
        "BackendAccessException_7cb5161f"
      ]
    ],
    "from_imports_typing": [],
    "extends_map": {
      "com.sun.star.configuration.backend.BackendAccessException": "BackendAccessException_7cb5161f"
    },
    "quote": [],
    "typings": [],
    "requires_typing": false,
    "full_imports": {
      "general": [
        "com.sun.star.configuration.backend.BackendAccessException"
      ],
      "typing": []
    },
    "imports": [],
    "name": "InsufficientAccessRightsException",
    "namespace": "com.sun.star.configuration.backend",
    "extends": [
      "com.sun.star.configuration.backend.BackendAccessException"
    ],
    "desc": [
      "Exception thrown when access to the underlying backend fails because of insufficient access rights to some needed resource.",
      "",
      "Examples of this include",
      "",
      "**since**",
      "",
      "    OOo 1.1.2"
    ],
    "url": "https://api.libreoffice.org/docs/idl/ref/exceptioncom_1_1sun_1_1star_1_1configuration_1_1backend_1_1InsufficientAccessRightsException.html",
    "items": {}
  }
}