{
  "id": "uno-ooo-parser",
  "version": "0.1.28",
  "libre_office_ver": "7.2",
  "type": "struct",
  "name": "VertOrientationFormat",
  "namespace": "com.sun.star.text",
  "parser_args": {
    "sort": false,
    "long_names": true,
    "remove_parent_inherited": true
  },
  "writer_args": {
    "sort": true,
    "dynamic_struct": true,
    "include_desc": true
  },
  "data": {
    "name": "VertOrientationFormat",
    "namespace": "com.sun.star.text",
    "url": "https://api.libreoffice.org/docs/idl/ref/structcom_1_1sun_1_1star_1_1text_1_1VertOrientationFormat.html",
    "from_imports": [],
    "from_imports_typing": [],
    "extends_map": {},
    "quote": [],
    "typings": [],
    "requires_typing": false,
    "full_imports": {
      "general": [],
      "typing": []
    },
    "fullname": "com.sun.star.text.VertOrientationFormat",
    "desc": [
      "describes the vertical orientation of an object.",
      "",
      "If VerticalOrientation == VERT_NONE, then the value \\\"YPos\\\" describes the distance from the top of the context. Otherwise \\\"YPos\\\" is ignored."
    ],
    "imports": [],
    "extends": [],
    "items": [
      {
        "name": "YPos",
        "type": "int",
        "origtype": null,
        "origin": "long",
        "desc": [
          "contains the distance from top.",
          "",
          "Only valid if the property VerticalOrientation contains the value VERT_NONE."
        ]
      },
      {
        "name": "VerticalOrientation",
        "type": "int",
        "origtype": null,
        "origin": "short",
        "desc": [
          "determines the vertical alignment of an object.",
          "",
          "The values refer to com.sun.star.VertOrientation."
        ]
      },
      {
        "name": "VerticalRelation",
        "type": "int",
        "origtype": null,
        "origin": "short",
        "desc": [
          "determines the reference position of the vertical alignment."
        ]
      }
    ]
  }
}