{
  "id": "uno-ooo-parser",
  "version": "0.1.14",
  "libre_office_ver": "7.2",
  "name": "DialogProvider",
  "type": "service",
  "namespace": "com.sun.star.awt",
  "parser_args": {
    "sort": true
  },
  "writer_args": {
    "include_desc": true
  },
  "data": {
    "from_imports": [
      [
        ".x_dialog_provider",
        "XDialogProvider"
      ]
    ],
    "from_imports_typing": [
      [
        "..frame.x_model",
        "XModel"
      ],
      [
        "..container.x_name_container",
        "XNameContainer"
      ],
      [
        "..script.x_script_listener",
        "XScriptListener"
      ],
      [
        "..io.x_input_stream",
        "XInputStream"
      ]
    ],
    "quote": [
      "XModel",
      "XNameContainer",
      "XInputStream",
      "XScriptListener"
    ],
    "typings": [],
    "requires_typing": true,
    "name": "DialogProvider",
    "imports": [],
    "namespace": "com.sun.star.awt",
    "extends": [
      "com.sun.star.awt.XDialogProvider"
    ],
    "desc": [
      "Specifies a provider for dialogs implementing the com.sun.star.awt.XDialog interface."
    ],
    "url": "https://api.libreoffice.org/docs/idl/ref/servicecom_1_1sun_1_1star_1_1awt_1_1DialogProvider.html",
    "items": {
      "methods": [
        {
          "name": "createWithModel",
          "returns": "None",
          "desc": [],
          "raises": [],
          "args": [
            [
              "Model",
              "XModel",
              "in"
            ]
          ]
        },
        {
          "name": "createWithModelAndScripting",
          "returns": "None",
          "desc": [],
          "raises": [],
          "args": [
            [
              "Model",
              "XModel",
              "in"
            ],
            [
              "InStream",
              "XInputStream",
              "in"
            ],
            [
              "DialogLib",
              "XNameContainer",
              "in"
            ],
            [
              "ScriptListener",
              "XScriptListener",
              "in"
            ]
          ]
        }
      ]
    }
  }
}