{
  "id": "uno-ooo-parser",
  "version": "0.1.3",
  "timestamp": "2021-12-17 11:17:37+00:00",
  "name": "XSimpleCanvas",
  "type": "interface",
  "namespace": "com.sun.star.rendering",
  "parser_args": {
    "sort": true
  },
  "writer_args": {},
  "data": {
    "from_imports": [
      [
        "..uno.x_interface",
        "XInterface"
      ]
    ],
    "from_imports_typing": [],
    "name": "XSimpleCanvas",
    "imports": [],
    "namespace": "com.sun.star.rendering",
    "extends": [
      "com.sun.star.uno.XInterface"
    ],
    "desc": [
      "Provides the basic graphical output operations for a canvas.",
      "",
      "This interface is a simplified version of the XCanvas interface. It holds explicit state, i.e. the pen and fill color, the current transformation, clip and font are persistently remembered.",
      "",
      "In contrast to the XCanvas interface, XSimpleCanvas does not distinguish between stroke and fill operations; instead, switching between stroke and fill (or taking both) works by setting appropriate pen and fill colors."
    ],
    "url": "https://api.libreoffice.org/docs/idl/ref/interfacecom_1_1sun_1_1star_1_1rendering_1_1XSimpleCanvas.html",
    "items": {}
  }
}