{
  "id": "uno-ooo-parser",
  "version": "0.1.8",
  "timestamp": "2021-12-28 20:10:37+00:00",
  "name": "SortFieldType",
  "type": "enum",
  "namespace": "com.sun.star.util",
  "parser_args": {
    "sort": true
  },
  "writer_args": {},
  "data": {
    "name": "SortFieldType",
    "ns": "com.sun.star.util",
    "url": "https://api.libreoffice.org/docs/idl/ref/namespacecom_1_1sun_1_1star_1_1util.html#aa222808b6dd3437074e57760d8e15a83",
    "quote": [],
    "typings": [],
    "desc": "",
    "items": [
      {
        "name": "ALPHANUMERIC",
        "value": "ALPHANUMERIC",
        "desc": [
          "sort field contains text data."
        ]
      },
      {
        "name": "AUTOMATIC",
        "value": "AUTOMATIC",
        "desc": [
          "type is determined automatically."
        ]
      },
      {
        "name": "NUMERIC",
        "value": "NUMERIC",
        "desc": [
          "sort field contains numerical data."
        ]
      }
    ]
  }
}