{
  "id": "uno-ooo-parser",
  "version": "0.1.16",
  "libre_office_ver": "7.2",
  "name": "XUpdatable2",
  "type": "interface",
  "namespace": "com.sun.star.util",
  "parser_args": {
    "sort": true,
    "long_names": true,
    "remove_parent_inherited": true
  },
  "writer_args": {
    "include_desc": true
  },
  "data": {
    "from_imports": [
      [
        ".x_updatable",
        "XUpdatable",
        "x_updatable_i"
      ]
    ],
    "from_imports_typing": [],
    "extends_map": {
      "com.sun.star.util.XUpdatable": "x_updatable_i"
    },
    "quote": [],
    "typings": [],
    "requires_typing": false,
    "name": "XUpdatable2",
    "imports": [],
    "namespace": "com.sun.star.util",
    "extends": [
      "com.sun.star.util.XUpdatable"
    ],
    "desc": [
      "This interface extends XUpdatable in order to provide more fine-tuned update modes.",
      "",
      "When performing a soft update, the implementor may decide not to update in certain cases, such as when the controller is locked. When performing a hard update, on the other hand, the implementor should perform update more aggressively even when the controller is locked."
    ],
    "url": "https://api.libreoffice.org/docs/idl/ref/interfacecom_1_1sun_1_1star_1_1util_1_1XUpdatable2.html",
    "items": {
      "methods": [
        {
          "name": "updateHard",
          "returns": "None",
          "desc": [
            "Perform update, even when the controller is locked."
          ],
          "raises": [],
          "args": []
        },
        {
          "name": "updateSoft",
          "returns": "None",
          "desc": [
            "Perform update, but update may not always be performed especially when the controller is locked."
          ],
          "raises": [],
          "args": []
        }
      ]
    }
  }
}