{
  "id": "uno-ooo-parser",
  "version": "2024.2.0",
  "libre_office_ver": "2024.2",
  "name": "PlaceholderType",
  "type": "const",
  "pytype": "int",
  "namespace": "com.sun.star.text",
  "parser_args": {
    "sort": false,
    "remove_parent_inherited": true
  },
  "writer_args": {
    "hex": false,
    "flags": false,
    "include_desc": true
  },
  "data": {
    "name": "PlaceholderType",
    "namespace": "com.sun.star.text",
    "url": "https://api.libreoffice.org/docs/idl/ref/namespacecom_1_1sun_1_1star_1_1text_1_1PlaceholderType.html",
    "flags": false,
    "pytype": "int",
    "allow_db": true,
    "quote": [],
    "typings": [],
    "requires_typing": false,
    "from_imports": [],
    "from_imports_typing": [],
    "fullname": "com.sun.star.text.PlaceholderType",
    "desc": [
      "These constants define how the place-holder text fields act in a document."
    ],
    "items": [
      {
        "name": "TEXT",
        "type": "int",
        "value_type": "INTEGER",
        "value": 0,
        "lines": [
          "The field represents a piece of text."
        ]
      },
      {
        "name": "TABLE",
        "type": "int",
        "value_type": "INTEGER",
        "value": 1,
        "lines": [
          "The field initiates the insertion of a text table."
        ]
      },
      {
        "name": "TEXTFRAME",
        "type": "int",
        "value_type": "INTEGER",
        "value": 2,
        "lines": [
          "The field initiates the insertion of a text frame."
        ]
      },
      {
        "name": "GRAPHIC",
        "type": "int",
        "value_type": "INTEGER",
        "value": 3,
        "lines": [
          "The field initiates the insertion of a graphic object."
        ]
      },
      {
        "name": "OBJECT",
        "type": "int",
        "value_type": "INTEGER",
        "value": 4,
        "lines": [
          "The field initiates the insertion of an embedded object."
        ]
      }
    ]
  }
}